cocosuite-0.1.0.dist-info/METADATA
cocosuite-0.1.0.dist-info/WHEEL
cocosuite-0.1.0.dist-info/licenses/LICENSE
cocotoolkit/__init__.py
cocosuite-0.1.0.dist-info/RECORD
