Metadata-Version: 2.1
Name: cocosuite
Version: 0.1.0
Summary: A toolkit for COCO dataset
Author-Email: =?utf-8?q?Jorge_N=C3=BA=C3=B1ez_Santiago?= <jorge.nusan@gmail.com>
License: MIT
Classifier: Programming Language :: Python :: 3
Classifier: License :: OSI Approved :: MIT License
Classifier: Operating System :: OS Independent
Project-URL: Homepage, https://github.com/jorgenusan/cocosuite
Project-URL: Issues, https://github.com/jorgenusan/cocosuite/issues
Project-URL: Documentation, https://github.com/jorgenusan/cocosuite/blob/main/README.md
Requires-Python: >=3.10
Requires-Dist: numpy==2.0.0
Requires-Dist: matplotlib==3.9.0
Requires-Dist: pre-commit==3.7.1
Requires-Dist: loguru==0.7.2
Requires-Dist: pytest==8.2.2
Requires-Dist: fire==0.6.0
Requires-Dist: pathlib==1.0.1
